lambdahelper/__init__ (Autosaved).py
lambdahelper/__init__.py
lambdahelper/http.py
aws_lambda_helper-0.0.5.dist-info/METADATA
aws_lambda_helper-0.0.5.dist-info/WHEEL
aws_lambda_helper-0.0.5.dist-info/top_level.txt
aws_lambda_helper-0.0.5.dist-info/RECORD
