Metadata-Version: 2.1
Name: aws-lambda-helper
Version: 0.0.5
Summary: A python library for AWS Lambda functions
Home-page: https://github.com/Just4test/aws-lambda-helper
Author: Just4test
Author-email: myservice@just4test.net
License: wtfpl
Keywords: aws,lambda
Platform: any
Classifier: Development Status :: 3 - Alpha
Classifier: Programming Language :: Python :: 3 :: Only
Requires-Dist: boto3
